fast_reading-0.1.2.dist-info/METADATA
fast_reading-0.1.2.dist-info/WHEEL
fast_reading-0.1.2.dist-info/entry_points.txt
fast_reading/_core.pyi
fast_reading/__init__.py
fast_reading/_core.cpython-39-x86_64-linux-gnu.so
fast_reading-0.1.2.dist-info/RECORD
