Metadata-Version: 2.4
Name: fast-reading
Version: 0.1.2
Classifier: Development Status :: 4 - Beta
Classifier: Intended Audience :: Developers
Classifier: License :: OSI Approved :: MIT License
Classifier: Programming Language :: Python
Classifier: Programming Language :: Python :: 3
Classifier: Programming Language :: Python :: 3.9
Classifier: Programming Language :: Python :: 3.10
Classifier: Programming Language :: Python :: 3.11
Classifier: Programming Language :: Python :: 3.12
Classifier: Operating System :: OS Independent
Classifier: Topic :: Software Development :: Libraries
Classifier: Topic :: Internet :: WWW/HTTP
Summary: A fast reading file library for Python
Keywords: python,rust,pyo3,file,read,reading,readline,readlines,readall,readallline,readalllines
Author-email: vffuunnyy <vffuunnyy@gmail.com>
Requires-Python: >=3.9
